wagtail_meta_preview/__init__.py
wagtail_meta_preview/meta_settings.py
wagtail_meta_preview/panels.py
wagtail_meta_preview/utils.py
wagtail_meta_preview/version.py
wagtail_meta_preview/views.py
wagtail_meta_preview/wagtail_hooks.py
wagtail_meta_preview/static/wagtail_meta_preview/wagtail-meta-preview.css
wagtail_meta_preview/static/wagtail_meta_preview/wagtail-meta-preview.js
wagtail_meta_preview/templates/wagtail_meta_preview/_facebook.html
wagtail_meta_preview/templates/wagtail_meta_preview/_google.html
wagtail_meta_preview/templates/wagtail_meta_preview/_twitter.html
wagtail_meta_preview/templates/wagtail_meta_preview/preview_panel.html
wagtail_meta_preview-4.2.1.dist-info/LICENSE
wagtail_meta_preview-4.2.1.dist-info/METADATA
wagtail_meta_preview-4.2.1.dist-info/WHEEL
wagtail_meta_preview-4.2.1.dist-info/top_level.txt
wagtail_meta_preview-4.2.1.dist-info/RECORD
