Metadata-Version: 2.2
Name: wagtail-meta-preview
Version: 4.2.1
Summary: Add preview panels for meta data to wagtail
Home-page: https://github.com/Frojd/wagtail-meta-preview
Author: Andreas Bernacca
Author-email: ante.bernacca@gmail.com
License: MIT License
Project-URL: Source, https://github.com/Frojd/wagtail-meta-preview/
Project-URL: Changelog, https://github.com/Frojd/wagtail-meta-preview/blob/main/CHANGELOG.md
Classifier: Environment :: Web Environment
Classifier: Intended Audience :: Developers
Classifier: Operating System :: OS Independent
Classifier: Programming Language :: Python
Classifier: Programming Language :: Python :: 3.9
Classifier: Programming Language :: Python :: 3.10
Classifier: Programming Language :: Python :: 3.11
Classifier: Programming Language :: Python :: 3.12
Classifier: Programming Language :: Python :: 3.13
Classifier: Framework :: Django
Classifier: Framework :: Wagtail
Classifier: Framework :: Wagtail :: 5
Classifier: Framework :: Wagtail :: 6
Classifier: License :: OSI Approved :: MIT License
License-File: LICENSE
Requires-Dist: wagtail>=5.2
Provides-Extra: testing
Requires-Dist: black; extra == "testing"
Requires-Dist: coverage; extra == "testing"
Dynamic: author
Dynamic: author-email
Dynamic: classifier
Dynamic: description
Dynamic: description-content-type
Dynamic: home-page
Dynamic: license
Dynamic: project-url
Dynamic: provides-extra
Dynamic: requires-dist
Dynamic: summary
